mkninja/stamp
mkninja/__main__.py
mkninja/_core.py
mkninja/manifest
mkninja/__init__.py
mkninja/findglob
mkninja-0.2.2.dist-info/METADATA
mkninja-0.2.2.dist-info/entry_points.txt
mkninja-0.2.2.dist-info/RECORD
mkninja-0.2.2.dist-info/top_level.txt
mkninja-0.2.2.dist-info/WHEEL
