Metadata-Version: 2.1
Name: mkninja
Version: 0.2.2
Summary: A python front-end for ninja
Home-page: https://github.com/rexroni/mkninja
Author: Rex Roni
Author-email: rexroni@splintermail.com
Classifier: Programming Language :: Python :: 3
Classifier: License :: OSI Approved :: The Unlicense (Unlicense)
Classifier: Operating System :: OS Independent
Requires-Python: >=3.6
